mln_converter/__init__.py
mln_converter/__main__.py
mln_converter/converter.py
mln_converter/record.py
mln_converter-0.2.0.dist-info/LICENSE
mln_converter-0.2.0.dist-info/METADATA
mln_converter-0.2.0.dist-info/WHEEL
mln_converter-0.2.0.dist-info/entry_points.txt
mln_converter-0.2.0.dist-info/RECORD
