Metadata-Version: 2.1
Name: mln-converter
Version: 0.2.0
Summary: Converts exported data from Minuteman Library Network reading history.
License: MIT
Author: Hugh Enxing
Author-email: deeoh@woodforsheep.trade
Requires-Python: >=3.11,<4.0
Classifier: License :: OSI Approved :: MIT License
Classifier: Programming Language :: Python :: 3
Classifier: Programming Language :: Python :: 3.11
